Metadata-Version: 2.1
Name: easy-pyinstaller
Version: 0.0.21
Summary: # Objetivo
Author: Igor Polegato
Author-email: 
License: MIT License
Keywords: ip-pyinstaller
License-File: LICENSE
